{
"records": [
  {
    "ac": "A332",
    "lu": "2022-07-06T15:16:00+0200",
    "typ": "P",
    "al": "DE",
    "fnr": "DE 2032",
    "terminal": "1",
    "halle": "C",
    "schedArr": "2022-07-06T16:00:00-0700",
    "schalter": "759-770",
    "duration": 645,
    "s": false,
    "iata": "SEA",
    "sched": "2022-07-06T14:15:00+0200",
    "reg": "DAIYD",
    "apname": "Seattle",
    "id": "d20220706de2032",
    "gate": "B44",
    "stops": 0,
    "lang": "en",
    "alname": "Condor",
    "flstatus": 0,
    "status": "Boarding"
  },
  {
    "ac": "TRS",
    "lu": "2022-07-06T15:16:00+0200",
    "typ": "P",
    "al": "LH",
    "fnr": "LH 3515",
    "terminal": "1",
    "esti": "2022-07-06T14:36:00+0200",
    "s": false,
    "iata": "QDU",
    "sched": "2022-07-06T14:36:00+0200",
    "reg": "",
    "apname": "Dusseldorf Main St.",
    "ausgang": "",
    "id": "a20220706lh3515",
    "lang": "en",
    "alname": "Lufthansa",
    "flstatus": 1,
    "status": "on position"
  },
  {
    "ac": "TRS",
    "lu": "2022-07-06T15:16:00+0200",
    "typ": "P",
    "al": "LH",
    "fnr": "LH 3616",
    "terminal": "1",
    "halle": "A",
    "esti": "2022-07-06T14:38:00+0200",
    "schalter": "",
    "s": false,
    "iata": "QKL",
    "sched": "2022-07-06T14:09:00+0200",
    "reg": "",
    "apname": "Cologne Main Station",
    "id": "d20220706lh3616",
    "gate": "T6",
    "lang": "en",
    "alname": "Lufthansa",
    "flstatus": 3,
    "status": "closed"
  },
  {
    "ac": "A333",
    "bag": ["55"],
    "lu": "2022-07-06T15:16:00+0200",
    "typ": "P",
    "al": "XC",
    "fnr": "XC 3143",
    "terminal": "2",
    "halle": "E",
    "esti": "2022-07-06T14:24:00+0200",
    "duration": 230,
    "s": false,
    "iata": "AYT",
    "sched": "2022-07-06T14:20:00+0200",
    "reg": "9HLEON",
    "apname": "Antalya",
    "ausgang": "E",
    "id": "a20220706xc3143",
    "lang": "en",
    "alname": "Corendon Airlines",
    "schedDep": "2022-07-06T11:30:00+0300",
    "flstatus": 1,
    "status": "baggage delivery"
  },
  {
    "ac": "CRJ9",
    "lu": "2022-07-06T15:16:00+0200",
    "typ": "P",
    "al": "SK",
    "fnr": "SK 4756",
    "terminal": "1",
    "halle": "A",
    "esti": "2022-07-06T14:37:00+0200",
    "schedArr": "2022-07-06T16:15:00+0200",
    "schalter": "263-461",
    "cs": ["LH 6280", "OU 5672"],
    "duration": 120,
    "s": false,
    "iata": "OSL",
    "sched": "2022-07-06T14:15:00+0200",
    "reg": "EIFPT",
    "apname": "Oslo-Gardermoen",
    "id": "d20220706sk4756",
    "gate": "B6",
    "stops": 0,
    "lang": "en",
    "alname": "SAS Scandinavian Airlines",
    "flstatus": 0,
    "status": "departed"
  },
  {
    "ac": "A319",
    "bag": ["43"],
    "lu": "2022-07-06T15:16:00+0200",
    "typ": "P",
    "al": "RJ",
    "fnr": "RJ 125",
    "terminal": "2",
    "halle": "D",
    "esti": "2022-07-06T14:45:00+0200",
    "duration": 285,
    "s": false,
    "iata": "AMM",
    "sched": "2022-07-06T14:35:00+0200",
    "reg": "JYAYZ",
    "apname": "Amman-Queen Alia",
    "ausgang": "D",
    "id": "a20220706rj125",
    "lang": "en",
    "alname": "Royal Jordanian Airlines",
    "schedDep": "2022-07-06T10:50:00+0300",
    "flstatus": 1,
    "status": "baggage delivery"
  },
  {
    "ac": "TRS",
    "lu": "2022-07-06T15:16:00+0200",
    "typ": "P",
    "al": "LH",
    "fnr": "LH 3692",
    "terminal": "1",
    "halle": "A",
    "schalter": "",
    "s": false,
    "iata": "QPP",
    "sched": "2022-07-06T14:09:00+0200",
    "reg": "",
    "rouname": "Goettingen Central",
    "apname": "Berlin Main Station",
    "rou": "ZEU",
    "id": "d20220706lh3692",
    "gate": "T4",
    "lang": "en",
    "alname": "Lufthansa",
    "flstatus": 3,
    "status": "closed"
  },
  {
    "ac": "A20N",
    "lu": "2022-07-06T15:16:00+0200",
    "typ": "P",
    "al": "LH",
    "fnr": "LH 875",
    "terminal": "1",
    "halle": "A",
    "esti": "2022-07-06T15:08:00+0200",
    "cs": ["AC 9675", "UA 9130"],
    "duration": 125,
    "s": false,
    "iata": "BGO",
    "sched": "2022-07-06T14:50:00+0200",
    "reg": "DAINK",
    "apname": "Bergen",
    "ausgang": "",
    "id": "a20220706lh875",
    "lang": "en",
    "alname": "Lufthansa",
    "schedDep": "2022-07-06T12:45:00+0200",
    "flstatus": 1,
    "status": "landed"
  },
  {
    "ac": "A338",
    "lu": "2022-07-06T15:16:00+0200",
    "typ": "P",
    "al": "KU",
    "fnr": "KU 172",
    "terminal": "2",
    "halle": "D",
    "esti": "2022-07-06T15:25:00+0200",
    "schedArr": "2022-07-06T20:40:00+0300",
    "schalter": "866-868",
    "duration": 315,
    "s": false,
    "iata": "KWI",
    "sched": "2022-07-06T14:25:00+0200",
    "reg": "9KAPG",
    "apname": "Kuwait",
    "id": "d20220706ku172",
    "gate": "D5",
    "stops": 0,
    "lang": "en",
    "alname": "Kuwait Airways",
    "flstatus": 0,
    "status": "ready for Boarding"
  },
  {
    "ac": "B789",
    "bag": ["53"],
    "lu": "2022-07-06T15:16:00+0200",
    "typ": "P",
    "al": "SV",
    "fnr": "SV 179",
    "terminal": "2",
    "halle": "E",
    "esti": "2022-07-06T14:57:00+0200",
    "duration": 360,
    "s": false,
    "iata": "RUH",
    "sched": "2022-07-06T14:45:00+0200",
    "reg": "HZARG",
    "apname": "Riyadh",
    "ausgang": "E",
    "id": "a20220706sv179",
    "lang": "en",
    "alname": "Saudia",
    "schedDep": "2022-07-06T09:45:00+0300",
    "flstatus": 1,
    "status": "on position"
  },
  {
    "ac": "E190",
    "bag": ["44"],
    "lu": "2022-07-06T15:16:00+0200",
    "typ": "P",
    "al": "FB",
    "fnr": "FB 437",
    "terminal": "2",
    "halle": "D",
    "esti": "2022-07-06T14:24:00+0200",
    "cs": ["QR 5559"],
    "duration": 145,
    "s": false,
    "iata": "SOF",
    "sched": "2022-07-06T14:25:00+0200",
    "reg": "LZBUR",
    "apname": "Sofia",
    "ausgang": "D",
    "id": "a20220706fb437",
    "lang": "en",
    "alname": "Bulgaria Air",
    "schedDep": "2022-07-06T13:00:00+0300",
    "flstatus": 1,
    "status": "baggage delivery"
  },
  {
    "ac": "TRS",
    "lu": "2022-07-06T15:16:00+0200",
    "typ": "P",
    "al": "LH",
    "fnr": "LH 3514",
    "terminal": "1",
    "halle": "A",
    "schalter": "",
    "s": false,
    "iata": "QDU",
    "sched": "2022-07-06T14:24:00+0200",
    "reg": "",
    "apname": "Dusseldorf Main St.",
    "id": "d20220706lh3514",
    "gate": "T7",
    "lang": "en",
    "alname": "Lufthansa",
    "flstatus": 3,
    "status": "closed"
  },
  {
    "ac": "TRS",
    "lu": "2022-07-06T15:16:00+0200",
    "typ": "P",
    "al": "LH",
    "fnr": "LH 3477",
    "terminal": "1",
    "esti": "2022-07-06T14:21:00+0200",
    "s": false,
    "iata": "ZMU",
    "sched": "2022-07-06T14:21:00+0200",
    "reg": "",
    "rouname": "Wuerzburg Central",
    "apname": "Munich Central St.",
    "rou": "QWU",
    "ausgang": "",
    "id": "a20220706lh3477",
    "lang": "en",
    "alname": "Lufthansa",
    "flstatus": 1,
    "status": "on position"
  },
  {
    "ac": "A343",
    "lu": "2022-07-06T15:16:00+0200",
    "typ": "P",
    "al": "LH",
    "fnr": "LH 542",
    "terminal": "1",
    "halle": "A",
    "esti": "2022-07-06T14:50:00+0200",
    "schedArr": "2022-07-06T18:59:00-0500",
    "schalter": "263-461",
    "cs": ["AV 6503", "EY 4162", "LX 4030"],
    "duration": 699,
    "s": false,
    "iata": "BOG",
    "sched": "2022-07-06T14:20:00+0200",
    "reg": "DAIGP",
    "apname": "Bogota",
    "id": "d20220706lh542",
    "gate": "C13",
    "stops": 0,
    "lang": "en",
    "alname": "Lufthansa",
    "flstatus": 0,
    "status": "departed"
  },
  {
    "ac": "A333",
    "lu": "2022-07-06T15:16:00+0200",
    "typ": "P",
    "al": "LH",
    "fnr": "LH 630",
    "terminal": "1",
    "halle": "A",
    "esti": "2022-07-06T14:30:00+0200",
    "schedArr": "2022-07-06T22:35:00+0400",
    "schalter": "263-461",
    "cs": ["AC 9088", "UA 8904"],
    "duration": 385,
    "s": false,
    "iata": "DXB",
    "sched": "2022-07-06T14:10:00+0200",
    "reg": "DAIKI",
    "apname": "Dubai-International",
    "id": "d20220706lh630",
    "gate": "Z22",
    "stops": 0,
    "lang": "en",
    "alname": "Lufthansa",
    "flstatus": 0,
    "status": "departed"
  },
  {
    "ac": "A343",
    "lu": "2022-07-06T15:16:00+0200",
    "typ": "P",
    "al": "LH",
    "fnr": "LH 478",
    "terminal": "1",
    "halle": "A",
    "esti": "2022-07-06T14:55:00+0200",
    "schedArr": "2022-07-06T16:15:00-0400",
    "schalter": "263-461",
    "cs": ["AC 9633"],
    "duration": 485,
    "s": false,
    "iata": "YUL",
    "sched": "2022-07-06T14:10:00+0200",
    "reg": "DAIFD",
    "apname": "Montreal",
    "id": "d20220706lh478",
    "gate": "B25",
    "stops": 0,
    "lang": "en",
    "alname": "Lufthansa",
    "flstatus": 0,
    "status": "departed"
  },
  {
    "ac": "B763",
    "bag": ["36"],
    "lu": "2022-07-06T15:16:00+0200",
    "typ": "P",
    "al": "DE",
    "fnr": "DE 2081",
    "terminal": "1",
    "halle": "C",
    "esti": "2022-07-06T14:22:00+0200",
    "duration": 705,
    "s": false,
    "iata": "LAX",
    "sched": "2022-07-06T14:40:00+0200",
    "reg": "DABUH",
    "apname": "Los Angeles",
    "ausgang": "C1",
    "id": "a20220706de2081",
    "lang": "en",
    "alname": "Condor",
    "schedDep": "2022-07-05T17:55:00-0700",
    "flstatus": 1,
    "status": "on position"
  },
  {
    "ac": "E75L",
    "lu": "2022-07-06T15:16:00+0200",
    "typ": "P",
    "al": "KL",
    "fnr": "KL 1768",
    "terminal": "2",
    "halle": "D",
    "schedArr": "2022-07-06T15:35:00+0200",
    "schalter": "801-804",
    "duration": 80,
    "s": false,
    "iata": "AMS",
    "sched": "2022-07-06T14:15:00+0200",
    "reg": "PHEXJ",
    "apname": "Amsterdam",
    "id": "d20220706kl1768",
    "gate": "D26",
    "stops": 0,
    "lang": "en",
    "alname": "KLM Royal Dutch Airlines",
    "flstatus": 0,
    "status": "departed"
  },
  {
    "ac": "A343",
    "lu": "2022-07-06T15:16:00+0200",
    "typ": "P",
    "al": "LH",
    "fnr": "LH 451",
    "terminal": "1",
    "halle": "A",
    "esti": "2022-07-06T15:34:00+0200",
    "cs": ["UA 8900", "NZ 4203", "OS 7318", "SN 7245"],
    "duration": 665,
    "s": false,
    "iata": "LAX",
    "sched": "2022-07-06T14:45:00+0200",
    "reg": "DAIGY",
    "apname": "Los Angeles",
    "ausgang": "",
    "id": "a20220706lh451",
    "lang": "en",
    "alname": "Lufthansa",
    "schedDep": "2022-07-05T18:40:00-0700",
    "flstatus": 0,
    "status": ""
  },
  {
    "ac": "TRS",
    "lu": "2022-07-06T15:16:00+0200",
    "typ": "P",
    "al": "LH",
    "fnr": "LH 3565",
    "terminal": "1",
    "esti": "2022-07-06T14:35:00+0200",
    "s": false,
    "iata": "ZWS",
    "sched": "2022-07-06T14:35:00+0200",
    "reg": "",
    "apname": "Stuttgart Railway",
    "ausgang": "",
    "id": "a20220706lh3565",
    "lang": "en",
    "alname": "Lufthansa",
    "flstatus": 1,
    "status": "on position"
  },
  {
    "ac": "A332",
    "lu": "2022-07-06T15:16:00+0200",
    "typ": "P",
    "al": "DE",
    "fnr": "DE 2032",
    "terminal": "1",
    "halle": "C",
    "schedArr": "2022-07-06T16:00:00-0700",
    "schalter": "759-770",
    "duration": 645,
    "s": false,
    "iata": "SEA",
    "sched": "2022-07-06T14:15:00+0200",
    "reg": "DAIYD",
    "apname": "Seattle",
    "id": "d20220706de2032",
    "gate": "B44",
    "stops": 0,
    "lang": "en",
    "alname": "Condor-copy",
    "flstatus": 0,
    "status": "Boarding"
  },
  {
    "ac": "TRS",
    "lu": "2022-07-06T15:16:00+0200",
    "typ": "P",
    "al": "LH",
    "fnr": "LH 3515",
    "terminal": "1",
    "esti": "2022-07-06T14:36:00+0200",
    "s": false,
    "iata": "QDU",
    "sched": "2022-07-06T14:36:00+0200",
    "reg": "",
    "apname": "Dusseldorf Main St.",
    "ausgang": "",
    "id": "a20220706lh3515",
    "lang": "en",
    "alname": "Lufthansa-copy",
    "flstatus": 1,
    "status": "on position"
  },
  {
    "ac": "TRS",
    "lu": "2022-07-06T15:16:00+0200",
    "typ": "P",
    "al": "LH",
    "fnr": "LH 3616",
    "terminal": "1",
    "halle": "A",
    "esti": "2022-07-06T14:38:00+0200",
    "schalter": "",
    "s": false,
    "iata": "QKL",
    "sched": "2022-07-06T14:09:00+0200",
    "reg": "",
    "apname": "Cologne Main Station",
    "id": "d20220706lh3616",
    "gate": "T6",
    "lang": "en",
    "alname": "Lufthansa-copy",
    "flstatus": 3,
    "status": "closed"
  },
  {
    "ac": "A333",
    "bag": ["55"],
    "lu": "2022-07-06T15:16:00+0200",
    "typ": "P",
    "al": "XC",
    "fnr": "XC 3143",
    "terminal": "2",
    "halle": "E",
    "esti": "2022-07-06T14:24:00+0200",
    "duration": 230,
    "s": false,
    "iata": "AYT",
    "sched": "2022-07-06T14:20:00+0200",
    "reg": "9HLEON",
    "apname": "Antalya",
    "ausgang": "E",
    "id": "a20220706xc3143",
    "lang": "en",
    "alname": "Corendon Airlines-copy",
    "schedDep": "2022-07-06T11:30:00+0300",
    "flstatus": 1,
    "status": "baggage delivery"
  },
  {
    "ac": "CRJ9",
    "lu": "2022-07-06T15:16:00+0200",
    "typ": "P",
    "al": "SK",
    "fnr": "SK 4756",
    "terminal": "1",
    "halle": "A",
    "esti": "2022-07-06T14:37:00+0200",
    "schedArr": "2022-07-06T16:15:00+0200",
    "schalter": "263-461",
    "cs": ["LH 6280", "OU 5672"],
    "duration": 120,
    "s": false,
    "iata": "OSL",
    "sched": "2022-07-06T14:15:00+0200",
    "reg": "EIFPT",
    "apname": "Oslo-Gardermoen",
    "id": "d20220706sk4756",
    "gate": "B6",
    "stops": 0,
    "lang": "en",
    "alname": "SAS Scandinavian Airlines-copy",
    "flstatus": 0,
    "status": "departed"
  }
]
}
